README.rst
setup.py
wellfare
scripts/comparestruct
scripts/freeda
scripts/mincepies
scripts/specplot
scripts/wellfare-ff
wellfare/__init__.py
wellfare/atom.py
wellfare/constants.py
wellfare/conversions.py
wellfare/messages.py
wellfare/molecule.py
wellfare/parallelisation.py
wellfare/qmparser.py
wellfare/thermochemistry.py
wellfare.egg-info/PKG-INFO
wellfare.egg-info/SOURCES.txt
wellfare.egg-info/dependency_links.txt
wellfare.egg-info/requires.txt
wellfare.egg-info/top_level.txt