Metadata-Version: 1.2
Name: wellfare
Version: 1.0.4
Summary: WellFARe - The Wellington Fast Assessment of REactions
Home-page: https://github.com/matthiaslein/WellFARe
Author: Matthias Lein
Author-email: matthias.lein@gmail.com
License: GNU General Public License v3.0
Platform: UNKNOWN
Requires-Python: >=3.4
